poetry_date_version_plugin/__init__.py
poetry_date_version_plugin/plugin.py
poetry_date_version_plugin-2021.7.16_6.dist-info/entry_points.txt
poetry_date_version_plugin-2021.7.16_6.dist-info/COPYING.md
poetry_date_version_plugin-2021.7.16_6.dist-info/WHEEL
poetry_date_version_plugin-2021.7.16_6.dist-info/METADATA
poetry_date_version_plugin-2021.7.16_6.dist-info/RECORD
