Metadata-Version: 2.1
Name: poetry-date-version-plugin
Version: 2021.7.16-6
Summary: 
Author: Dustyn Gibson
Author-email: miigotu@gmail.com
Requires-Python: >=3.6.2,<4.0
Classifier: Programming Language :: Python :: 3
Classifier: Programming Language :: Python :: 3.7
Classifier: Programming Language :: Python :: 3.8
Classifier: Programming Language :: Python :: 3.9
Classifier: Programming Language :: Python :: 3.10
Requires-Dist: cleo (>=1.0.0a1,<2.0.0)
Requires-Dist: poetry (>=1.2.0a0)
